atmopy/__init__.py
atmopy/utils.py
atmopy/diehl22/__init__.py
atmopy/diehl22/constants.py
atmopy/diehl22/model.py
atmopy-0.1.0.dist-info/entry_points.txt
atmopy-0.1.0.dist-info/LICENSE
atmopy-0.1.0.dist-info/WHEEL
atmopy-0.1.0.dist-info/METADATA
atmopy-0.1.0.dist-info/RECORD
