Metadata-Version: 2.1
Name: atmopy
Version: 0.1.0
Summary: Atmopy 
Home-page: https://github.com/jorgepiloto/atmopy/
License: UNKNOWN
Keywords: aerospace,atmosphere,orbital mechanics
Author: Jorge M.G.
Author-email: jorge@on-orbit.dev
Requires-Python: >=3.6
Classifier: License :: OSI Approved :: MIT License
Classifier: Intended Audience :: Science/Research
Classifier: Operating System :: OS Independent
Classifier: Programming Language :: Python
Classifier: Programming Language :: Python :: 3
Classifier: Topic :: Scientific/Engineering
Classifier: Topic :: Scientific/Engineering :: Physics
Classifier: Topic :: Scientific/Engineering :: Astronomy
Requires-Dist: numpy
Requires-Dist: black ; extra == "dev"
Requires-Dist: isort ; extra == "dev"
Requires-Dist: pytest ; extra == "dev"
Requires-Dist: pytest-cov ; extra == "dev"
Requires-Dist: sphinx ; extra == "dev"
Requires-Dist: tox ; extra == "dev"
Project-URL: Source, https://github.com/jorgepiloto/atmopy
Project-URL: Tracker, https://github.com/jorgepiloto/atmopy/issues
Provides-Extra: dev
